{
  "doc_id": "synthetic_train_055",
  "source_pdf": "train/pdfs/synthetic_train_055.pdf",
  "attributes": {
    "has_oil_gas_reservations": true,
    "reservation_count": 3,
    "total_deeds": 6,
    "total_pages": 20
  },
  "deed_count": 6,
  "page_starts": [
    1,
    7,
    10,
    13,
    15,
    19
  ],
  "deeds": [
    {
      "index": 1,
      "page_start": 1,
      "page_end": 6,
      "source_file": "OR 276_4740.pdf",
      "has_oil_gas_reservations": false,
      "page_count": 6
    },
    {
      "index": 2,
      "page_start": 7,
      "page_end": 9,
      "source_file": "DB 347_434.pdf",
      "has_oil_gas_reservations": true,
      "page_count": 3
    },
    {
      "index": 3,
      "page_start": 10,
      "page_end": 12,
      "source_file": "Harrison DV 234_357.pdf",
      "has_oil_gas_reservations": false,
      "page_count": 3
    },
    {
      "index": 4,
      "page_start": 13,
      "page_end": 14,
      "source_file": "Brooke DB 74_249.pdf",
      "has_oil_gas_reservations": true,
      "page_count": 2
    },
    {
      "index": 5,
      "page_start": 15,
      "page_end": 18,
      "source_file": "Butler DB 1895_80 - 4.23.2025.pdf",
      "has_oil_gas_reservations": false,
      "page_count": 4
    },
    {
      "index": 6,
      "page_start": 19,
      "page_end": 20,
      "source_file": "Washington DB 704_223.pdf",
      "has_oil_gas_reservations": true,
      "page_count": 2
    }
  ],
  "validation": {
    "status": "synthetic",
    "issues": [],
    "n_starts_raw": 6,
    "n_starts_normalized": 6,
    "duplicates": {}
  },
  "qc": {
    "status": "synthetic",
    "issues": []
  },
  "metadata": {
    "generated_at": "2025-09-08T16:59:10.090061",
    "generator": "synthetic_dataset_generator",
    "seed": 42,
    "pdf_hash": "b0ee2d794f37f6392cfa85470581aacfc32d967e952d7351e1d9efed0dfb44ff"
  }
}