{
  "doc_id": "synthetic_train_074",
  "source_pdf": "train/pdfs/synthetic_train_074.pdf",
  "attributes": {
    "has_oil_gas_reservations": true,
    "reservation_count": 4,
    "total_deeds": 13,
    "total_pages": 42
  },
  "deed_count": 13,
  "page_starts": [
    1,
    4,
    7,
    11,
    17,
    20,
    22,
    24,
    26,
    27,
    29,
    35,
    41
  ],
  "deeds": [
    {
      "index": 1,
      "page_start": 1,
      "page_end": 3,
      "source_file": "Harrison DV 234_357.pdf",
      "has_oil_gas_reservations": false,
      "page_count": 3
    },
    {
      "index": 2,
      "page_start": 4,
      "page_end": 6,
      "source_file": "Armstrong DB 5269_327 - 4.23.2025.pdf",
      "has_oil_gas_reservations": true,
      "page_count": 3
    },
    {
      "index": 3,
      "page_start": 7,
      "page_end": 10,
      "source_file": "Allegheny DB 92_389.pdf",
      "has_oil_gas_reservations": false,
      "page_count": 4
    },
    {
      "index": 4,
      "page_start": 11,
      "page_end": 16,
      "source_file": "DV 192_833.pdf",
      "has_oil_gas_reservations": false,
      "page_count": 6
    },
    {
      "index": 5,
      "page_start": 17,
      "page_end": 19,
      "source_file": "OR 267_4753.pdf",
      "has_oil_gas_reservations": false,
      "page_count": 3
    },
    {
      "index": 6,
      "page_start": 20,
      "page_end": 21,
      "source_file": "Harrison DV 96_39.pdf",
      "has_oil_gas_reservations": false,
      "page_count": 2
    },
    {
      "index": 7,
      "page_start": 22,
      "page_end": 23,
      "source_file": "OR 16_217.pdf",
      "has_oil_gas_reservations": false,
      "page_count": 2
    },
    {
      "index": 8,
      "page_start": 24,
      "page_end": 25,
      "source_file": "Washington DB 704_223.pdf",
      "has_oil_gas_reservations": true,
      "page_count": 2
    },
    {
      "index": 9,
      "page_start": 26,
      "page_end": 26,
      "source_file": "Tuscawaras DV 539_793.pdf",
      "has_oil_gas_reservations": false,
      "page_count": 1
    },
    {
      "index": 10,
      "page_start": 27,
      "page_end": 28,
      "source_file": "DB 187-594.pdf",
      "has_oil_gas_reservations": false,
      "page_count": 2
    },
    {
      "index": 11,
      "page_start": 29,
      "page_end": 34,
      "source_file": "DV 217_352.pdf",
      "has_oil_gas_reservations": false,
      "page_count": 6
    },
    {
      "index": 12,
      "page_start": 35,
      "page_end": 40,
      "source_file": "DB 800_131.pdf",
      "has_oil_gas_reservations": true,
      "page_count": 6
    },
    {
      "index": 13,
      "page_start": 41,
      "page_end": 42,
      "source_file": "Brooke DB 74_249.pdf",
      "has_oil_gas_reservations": true,
      "page_count": 2
    }
  ],
  "validation": {
    "status": "synthetic",
    "issues": [],
    "n_starts_raw": 13,
    "n_starts_normalized": 13,
    "duplicates": {}
  },
  "qc": {
    "status": "synthetic",
    "issues": []
  },
  "metadata": {
    "generated_at": "2025-09-08T16:59:10.768755",
    "generator": "synthetic_dataset_generator",
    "seed": 42,
    "pdf_hash": "a3a14210099cc9d477084332d6251e562274c0e8d8da324f34ac021ec4640959"
  }
}